django_custom_user_migration/utils.py
django_custom_user_migration/models.py
django_custom_user_migration/__init__.py
django_custom_user_migration/management/__init__.py
django_custom_user_migration/management/commands/create_custom_user_populate_migration.py
django_custom_user_migration/management/commands/create_custom_user_schema_migration.py
django_custom_user_migration/management/commands/base.py
django_custom_user_migration/management/commands/create_custom_user_empty_migration.py
django_custom_user_migration/management/commands/create_custom_user_contenttypes_migration.py
django_custom_user_migration/management/commands/__init__.py
django_custom_user_migration-0.3.0.dist-info/RECORD
django_custom_user_migration-0.3.0.dist-info/DESCRIPTION.rst
django_custom_user_migration-0.3.0.dist-info/METADATA
django_custom_user_migration-0.3.0.dist-info/top_level.txt
django_custom_user_migration-0.3.0.dist-info/metadata.json
django_custom_user_migration-0.3.0.dist-info/WHEEL
