Metadata-Version: 2.0
Name: django-custom-user-migration
Version: 0.3.0
Summary: django_custom_user_migration will help you create a migration to using a custom User model with Django
Home-page: https://bitbucket.com/spookylukey/django_custom_user_migration
Author: Luke Plant
Author-email: L.Plant.98@cantab.net
License: BSD
Keywords: Django custom user model migration
Platform: UNKNOWN
Classifier: Development Status :: 2 - Pre-Alpha
Classifier: Framework :: Django
Classifier: Intended Audience :: Developers
Classifier: License :: OSI Approved :: BSD License
Classifier: Natural Language :: English
Classifier: Programming Language :: Python :: 2
Classifier: Programming Language :: Python :: 2.7
Classifier: Programming Language :: Python :: 3
Classifier: Programming Language :: Python :: 3.3
Classifier: Programming Language :: Python :: 3.4
Requires-Dist: Django (>=1.8)
